cobra_utils/__init__.py
cobra_utils/io/__init__.py
cobra_utils/io/load_data.py
cobra_utils/io/save_data.py
cobra_utils/query/__init__.py
cobra_utils/query/get_ids.py
cobra_utils/query/met_info.py
cobra_utils/query/rxn_info.py
cobra_utils/topology/__init__.py
cobra_utils/topology/reporter_metabolites.py
cobra_utils/topology/reporter_pathways.py
cobra_utils-0.3.1.dist-info/LICENSE
cobra_utils-0.3.1.dist-info/METADATA
cobra_utils-0.3.1.dist-info/WHEEL
cobra_utils-0.3.1.dist-info/top_level.txt
cobra_utils-0.3.1.dist-info/RECORD
